MANIFEST.in
README.md
requirements.txt
setup.py
lle7ch/__init__.py
lle7ch/lle.py
lle7ch/lleplan.py
lle7ch.egg-info/PKG-INFO
lle7ch.egg-info/SOURCES.txt
lle7ch.egg-info/dependency_links.txt
lle7ch.egg-info/entry_points.txt
lle7ch.egg-info/requires.txt
lle7ch.egg-info/top_level.txt